[
    {
      "id":1,
      "title":"Реал",
      "description":"Автомойка",
      "address":"Аптечный пер.,9",
      "distance": 3
    },
    {
      "id":2,
      "title":"Мой-ка! DS",
      "description":"Сеть автомоек самообслуживания",
      "address":"ул.Бетонная, 9Б, Гуково, Ростовская область",
      "distance": 120
    },
    {
      "id":3,
      "title":"Аква",
      "description":"Автомойка самообслуживания",
      "address":"ул.Бетонная, 9Б, Гуково, Ростовская область",
      "distance": 120
    }
    
  ]